DeepEnsemble/DeepEnsemble.py
DeepEnsemble/__init__.py
Test/__init__.py
Test/test.py
DeepEnsemble-0.0.3.dist-info/LICENSE
DeepEnsemble-0.0.3.dist-info/METADATA
DeepEnsemble-0.0.3.dist-info/WHEEL
DeepEnsemble-0.0.3.dist-info/top_level.txt
DeepEnsemble-0.0.3.dist-info/RECORD
