Metadata-Version: 2.1
Name: DeepEnsemble
Version: 0.0.3
Summary: An Wrapper for performing ensembling techniques on deep learning models
Home-page: https://github.com/induraj2020/DeepEnsemble.git
Author: Induraj P.Ramamurthy
Author-email: induraj.gandhian@yahoo.com
License: UNKNOWN
Platform: UNKNOWN
Classifier: Development Status :: 3 - Alpha
Classifier: Intended Audience :: Science/Research
Classifier: License :: OSI Approved :: MIT License
Classifier: Natural Language :: English
Classifier: Programming Language :: Python :: 3
Classifier: License :: OSI Approved :: MIT License
Classifier: Operating System :: OS Independent
Classifier: Topic :: Software Development :: Libraries :: Python Modules
Classifier: Topic :: Scientific/Engineering :: Artificial Intelligence
Requires-Python: >=3.7
License-File: LICENSE
